peoplefaceimage/__init__.py
peoplefaceimage/pacote.py
peoplefaceimage-0.0.8.dist-info/LICENSE
peoplefaceimage-0.0.8.dist-info/METADATA
peoplefaceimage-0.0.8.dist-info/WHEEL
peoplefaceimage-0.0.8.dist-info/top_level.txt
peoplefaceimage-0.0.8.dist-info/RECORD
