Metadata-Version: 2.1
Name: peoplefaceimage
Version: 0.0.8
Summary: Detecção de faces em imagens
Author: Victor Macedo, Luis Eduardo
Author-email: victmacc@ufpi.edu.br, duardos26@gmail.com
Classifier: Development Status :: 3 - Alpha
Classifier: Intended Audience :: Developers
Classifier: License :: OSI Approved :: MIT License
Classifier: Programming Language :: Python :: 3
Classifier: Programming Language :: Python :: 3.8
Classifier: Programming Language :: Python :: 3.9
Classifier: Programming Language :: Python :: 3.10
License-File: LICENSE
Requires-Dist: opencv-python
